odoo/addons/license_subscription/LICENSE
odoo/addons/license_subscription/README.rst
odoo/addons/license_subscription/__init__.py
odoo/addons/license_subscription/__manifest__.py
odoo/addons/license_subscription/demo/demo.xml
odoo/addons/license_subscription/i18n/de_CH.po
odoo/addons/license_subscription/images/screen.png
odoo/addons/license_subscription/models/__init__.py
odoo/addons/license_subscription/models/license_license.py
odoo/addons/license_subscription/models/sale_order.py
odoo/addons/license_subscription/models/sale_order_line.py
odoo/addons/license_subscription/readme/CONTRIBUTORS.md
odoo/addons/license_subscription/readme/DESCRIPTION.md
odoo/addons/license_subscription/readme/USAGE.md
odoo/addons/license_subscription/static/description/icon.png
odoo/addons/license_subscription/static/description/index.html
odoo/addons/license_subscription/tests/TEST_INSTRUCTIONS.rst
odoo/addons/license_subscription/views/sale_subscription_views.xml
odoo_addon_license_subscription-18.0.1.0.0.dist-info/METADATA
odoo_addon_license_subscription-18.0.1.0.0.dist-info/WHEEL
odoo_addon_license_subscription-18.0.1.0.0.dist-info/top_level.txt
odoo_addon_license_subscription-18.0.1.0.0.dist-info/RECORD
