Metadata-Version: 2.1
Name: odoo-addon-license_subscription
Version: 18.0.1.0.0
Requires-Python: >=3.10
Requires-Dist: odoo-addon-license_sale==18.0.*
Requires-Dist: odoo-addon-sale_order_line_pricelist_fixed_discount==18.0.*
Requires-Dist: odoo-addon-sale_triple_discount==18.0.*
Requires-Dist: odoo==18.0.*
Summary: Update license based on subscription changes.
Home-page: https://www.mint-system.ch/
License: OPL-1
Author: Mint System GmbH
Classifier: Programming Language :: Python
Classifier: Framework :: Odoo
Classifier: Framework :: Odoo :: 18.0
